domainNetwork/__init__.py
domainNetwork/__main__.py
domainNetwork/domain_network_main.py
domainNetwork/domain_network_utils.py
domainNetwork/network_generator.py
domainNetwork/tweet_reader.py
domainNetwork/url_processor.py
domain_network-0.1.2.dist-info/LICENSE
domain_network-0.1.2.dist-info/METADATA
domain_network-0.1.2.dist-info/WHEEL
domain_network-0.1.2.dist-info/top_level.txt
domain_network-0.1.2.dist-info/RECORD
