Metadata-Version: 2.1
Name: domain-network
Version: 0.1.2
Summary: Makes a network out of a URLs in a dataset of tweets
Home-page: https://git.science.uu.nl/research-it-support/domain_network
Author: Research-IT support
Author-email: p.zahedi@uu.nl
License: UNKNOWN
Platform: UNKNOWN
Classifier: Programming Language :: Python :: 3
Classifier: License :: OSI Approved :: MIT License
Classifier: Operating System :: OS Independent
Requires-Python: >=3.6
Requires-Dist: numpy
Requires-Dist: pandas
